medium_multiply_paulowiz/__init__.py
medium_multiply_paulowiz/multiplication.py
medium_multiply_paulowiz-0.2.0.dist-info/METADATA
medium_multiply_paulowiz-0.2.0.dist-info/WHEEL
medium_multiply_paulowiz-0.2.0.dist-info/top_level.txt
medium_multiply_paulowiz-0.2.0.dist-info/RECORD
