Metadata-Version: 2.1
Name: medium-multiply-paulowiz
Version: 0.2.0
Summary: Demo library
Home-page: https://medium-multiply.readthedocs.io/
Author: Paulo Mota
Author-email: p.mota@datacation.nl
License: MIT
Classifier: Intended Audience :: Developers
Classifier: License :: OSI Approved :: MIT License
Classifier: Programming Language :: Python
Classifier: Programming Language :: Python :: 3
Classifier: Programming Language :: Python :: 3.6
Classifier: Programming Language :: Python :: 3.7
Classifier: Programming Language :: Python :: 3.8
Classifier: Programming Language :: Python :: 3.9
Classifier: Operating System :: OS Independent
Requires-Dist: numpy
